mseep_zulipchat_mcp-2.3.1.dist-info/licenses/LICENSE
zulipchat_mcp/__init__.py
zulipchat_mcp/config.py
zulipchat_mcp/server.py
zulipchat_mcp/core/__init__.py
zulipchat_mcp/core/agent_tracker.py
zulipchat_mcp/core/cache.py
zulipchat_mcp/core/client.py
zulipchat_mcp/core/exceptions.py
zulipchat_mcp/core/security.py
zulipchat_mcp/core/commands/__init__.py
zulipchat_mcp/core/commands/engine.py
zulipchat_mcp/core/commands/workflows.py
zulipchat_mcp/integrations/__init__.py
zulipchat_mcp/integrations/registry.py
zulipchat_mcp/integrations/claude_code/__init__.py
zulipchat_mcp/integrations/claude_code/capabilities.py
zulipchat_mcp/integrations/claude_code/installer.py
zulipchat_mcp/integrations/gemini_cli/__init__.py
zulipchat_mcp/integrations/gemini_cli/capabilities.py
zulipchat_mcp/integrations/gemini_cli/installer.py
zulipchat_mcp/integrations/opencode/__init__.py
zulipchat_mcp/integrations/opencode/capabilities.py
zulipchat_mcp/integrations/opencode/installer.py
zulipchat_mcp/services/__init__.py
zulipchat_mcp/services/scheduler.py
zulipchat_mcp/tools/__init__.py
zulipchat_mcp/tools/agents.py
zulipchat_mcp/tools/commands.py
zulipchat_mcp/tools/messaging.py
zulipchat_mcp/tools/search.py
zulipchat_mcp/tools/streams.py
zulipchat_mcp/utils/__init__.py
zulipchat_mcp/utils/database.py
zulipchat_mcp/utils/health.py
zulipchat_mcp/utils/logging.py
zulipchat_mcp/utils/metrics.py
mseep_zulipchat_mcp-2.3.1.dist-info/METADATA
mseep_zulipchat_mcp-2.3.1.dist-info/WHEEL
mseep_zulipchat_mcp-2.3.1.dist-info/entry_points.txt
mseep_zulipchat_mcp-2.3.1.dist-info/top_level.txt
mseep_zulipchat_mcp-2.3.1.dist-info/RECORD
