Metadata-Version: 2.4
Name: mseep-zulipchat-mcp
Version: 2.3.1
Summary: MCP server for Zulip Chat integration
Author-email: mseep <support@skydeck.ai>
License-Expression: MIT
Project-URL: Homepage, https://github.com/akougkas/zulipchat-mcp
Project-URL: Documentation, https://github.com/akougkas/zulipchat-mcp#readme
Project-URL: Repository, https://github.com/akougkas/zulipchat-mcp.git
Project-URL: Issues, https://github.com/akougkas/zulipchat-mcp/issues
Project-URL: Changelog, https://github.com/akougkas/zulipchat-mcp/releases
Keywords: mcp,zulip,chat,ai,assistant
Classifier: Development Status :: 5 - Production/Stable
Classifier: Intended Audience :: Developers
Classifier: Operating System :: OS Independent
Classifier: Programming Language :: Python :: 3
Classifier: Programming Language :: Python :: 3.10
Classifier: Programming Language :: Python :: 3.11
Classifier: Programming Language :: Python :: 3.12
Classifier: Topic :: Communications :: Chat
Classifier: Topic :: Software Development :: Libraries :: Python Modules
Requires-Python: >=3.10
License-File: LICENSE
Requires-Dist: fastmcp>=0.1.0
Requires-Dist: httpx>=0.24.0
Requires-Dist: pydantic>=2.0.0
Requires-Dist: python-dotenv>=1.0.0
Requires-Dist: zulip>=0.9.0
Requires-Dist: structlog>=24.1.0
Requires-Dist: prometheus-client>=0.19.0
Requires-Dist: duckdb>=0.9.0
Dynamic: license-file
